[{"eventKey":"2014abca","name":"Western Canada"},{"eventKey":"2014arc","name":"Archimedes"},{"eventKey":"2014arfa","name":"Arkansas"},{"eventKey":"2014aroz","name":"Ozark Mountain Brawl"},{"eventKey":"2014audd","name":"Duel Down Under"},{"eventKey":"2014azch","name":"Arizona"},{"eventKey":"2014bc","name":"Battlecry"},{"eventKey":"2014bfbg","name":"Bluegrass"},{"eventKey":"2014bt","name":"Beantown"},{"eventKey":"2014cacc","name":null},{"eventKey":"2014cacg","name":null},{"eventKey":"2014cafc","name":"Fall Classic (Sat)"},{"eventKey":"2014cafc2","name":"Fall Classic (Sun)"},{"eventKey":"2014calb","name":"Los Angeles"},{"eventKey":"2014cama","name":"Central Valley"},{"eventKey":"2014casa","name":"Sacramento"},{"eventKey":"2014casb","name":"Inland Empire"},{"eventKey":"2014casd","name":"San Diego"},{"eventKey":"2014casj","name":"Silicon Valley"},{"eventKey":"2014cc","name":"Chezy Champs"},{"eventKey":"2014cmp","name":"Einstein"},{"eventKey":"2014code","name":"Colorado"},{"eventKey":"2014ctgro","name":"Groton"},{"eventKey":"2014cthar","name":"Hartford"},{"eventKey":"2014ctsc","name":"CT State Championship"},{"eventKey":"2014ctsou","name":"Southington"},{"eventKey":"2014ctss","name":"Suffield"},{"eventKey":"2014cttd","name":null},{"eventKey":"2014cur","name":"Curie"},{"eventKey":"2014dcwa","name":"Greater DC"},{"eventKey":"2014flfo","name":"South Florida"},{"eventKey":"2014flor","name":"Orlando"},{"eventKey":"2014flpp","name":"Panther Prowl"},{"eventKey":"2014flrc","name":null},{"eventKey":"2014gadu","name":"Peachtree"},{"eventKey":"2014gagr","name":"GRITS"},{"eventKey":"2014gal","name":"Galileo"},{"eventKey":"2014glbbb","name":null},{"eventKey":"2014hiho","name":"Hawaii"},{"eventKey":"2014ilch","name":"Midwest"},{"eventKey":"2014ilil","name":"Central Illinois"},{"eventKey":"2014ilrr","name":null},{"eventKey":"2014inbp","name":null},{"eventKey":"2014incm","name":null},{"eventKey":"2014inth","name":"Crossroads"},{"eventKey":"2014inwl","name":"Boilermaker"},{"eventKey":"2014ios","name":"Israeli Offseason"},{"eventKey":"2014iri","name":"IRI"},{"eventKey":"2014iroc","name":null},{"eventKey":"2014ista","name":"Israel"},{"eventKey":"2014lake","name":"Bayou"},{"eventKey":"2014mabos","name":"Northeastern University"},{"eventKey":"2014marc","name":"MARC"},{"eventKey":"2014mawor","name":"WPI"},{"eventKey":"2014mdba","name":"Chesapeake"},{"eventKey":"2014mdbb","name":null},{"eventKey":"2014melew","name":"Pine Tree"},{"eventKey":"2014mems","name":null},{"eventKey":"2014mibed","name":"Bedford"},{"eventKey":"2014mibg","name":null},{"eventKey":"2014micen","name":"Center Line"},{"eventKey":"2014micmp","name":"Michigan"},{"eventKey":"2014miesc","name":"Escanaba"},{"eventKey":"2014migul","name":"Gull Lake"},{"eventKey":"2014mihow","name":"Howell"},{"eventKey":"2014miket","name":"Kettering University"},{"eventKey":"2014mikk","name":"Kettering Kickoff"},{"eventKey":"2014milan","name":"Lansing"},{"eventKey":"2014miliv","name":"Livonia"},{"eventKey":"2014mimid","name":"Great Lakes Bay Region"},{"eventKey":"2014misjo","name":"St. Joseph"},{"eventKey":"2014misou","name":"Southfield"},{"eventKey":"2014mitry","name":"Troy"},{"eventKey":"2014mitvc","name":"Traverse City"},{"eventKey":"2014miwat","name":"Waterford"},{"eventKey":"2014miwmi","name":"West Michigan"},{"eventKey":"2014mm","name":"Monty Madness"},{"eventKey":"2014mndu","name":"Lake Superior"},{"eventKey":"2014mndu2","name":"Northern Lights"},{"eventKey":"2014mngggt","name":null},{"eventKey":"2014mnmi","name":"Minnesota 10000 Lakes"},{"eventKey":"2014mnmi2","name":"Minnesota North Star"},{"eventKey":"2014mnmmr","name":null},{"eventKey":"2014mogw","name":null},{"eventKey":"2014mokc","name":"Greater Kansas City"},{"eventKey":"2014mosl","name":"St. Louis"},{"eventKey":"2014mrcmp","name":"Mid-Atlantic Robotics"},{"eventKey":"2014mri","name":null},{"eventKey":"2014mttd","name":"MadTown ThrowDown"},{"eventKey":"2014mxmc","name":"Mexico City"},{"eventKey":"2014ncre","name":"North Carolina"},{"eventKey":"2014ncth","name":"THOR"},{"eventKey":"2014necmp","name":"New England"},{"eventKey":"2014new","name":"Newton"},{"eventKey":"2014nhbb","name":"Battle of the Bay"},{"eventKey":"2014nhdur","name":"UNH"},{"eventKey":"2014nhnas","name":"Granite State"},{"eventKey":"2014nhrr","name":null},{"eventKey":"2014njbe","name":null},{"eventKey":"2014njbri","name":"Bridgewater-Raritan"},{"eventKey":"2014njcli","name":"Clifton"},{"eventKey":"2014njdd","name":null},{"eventKey":"2014njfla","name":"Mt. Olive"},{"eventKey":"2014njmm","name":"MidKnight Mayhem"},{"eventKey":"2014njtab","name":"Lenape-Seneca"},{"eventKey":"2014nvlv","name":"Las Vegas"},{"eventKey":"2014nyli","name":"SBPLI Long Island"},{"eventKey":"2014nyny","name":"New York City"},{"eventKey":"2014nyro","name":"Finger Lakes"},{"eventKey":"2014nyrr","name":null},{"eventKey":"2014nytr","name":"New York Tech Valley"},{"eventKey":"2014nytv","name":"Tech Valley Robot Rumble"},{"eventKey":"2014ohci","name":"Queen City"},{"eventKey":"2014ohcl","name":"Buckeye"},{"eventKey":"2014ohcmp","name":"Ohio Champs"},{"eventKey":"2014ohmv","name":"mvrc"},{"eventKey":"2014ohri","name":"CORI"},{"eventKey":"2014okok","name":"Oklahoma"},{"eventKey":"2014onnb","name":"North Bay"},{"eventKey":"2014onto","name":"Greater Toronto East"},{"eventKey":"2014onto2","name":"Greater Toronto West"},{"eventKey":"2014onwa","name":"Waterloo"},{"eventKey":"2014onwi","name":"Windsor Essex Great Lakes"},{"eventKey":"2014orbb","name":null},{"eventKey":"2014orgg","name":null},{"eventKey":"2014orore","name":"Oregon City"},{"eventKey":"2014orosu","name":"Oregon State University"},{"eventKey":"2014orrr","name":null},{"eventKey":"2014orwil","name":"Wilsonville"},{"eventKey":"2014pagp","name":null},{"eventKey":"2014pahat","name":"Hatboro-Horsham"},{"eventKey":"2014paphi","name":"Springside Chestnut Hill"},{"eventKey":"2014papi","name":"Greater Pittsburgh"},{"eventKey":"2014parr","name":null},{"eventKey":"2014pncmp","name":"Autodesk PNW"},{"eventKey":"2014qcmo","name":"Festival de Robotique"},{"eventKey":"2014rismi","name":"Rhode Island"},{"eventKey":"2014rsr","name":null},{"eventKey":"2014scmb","name":"Palmetto"},{"eventKey":"2014scs","name":null},{"eventKey":"2014tnkn","name":"Smoky Mountains"},{"eventKey":"2014txda","name":"Dallas"},{"eventKey":"2014txho","name":"Lone Star"},{"eventKey":"2014txlu","name":"Hub City"},{"eventKey":"2014txrb","name":"RoboReboot"},{"eventKey":"2014txri","name":"Texas Robotics Invitational"},{"eventKey":"2014txrm","name":"Houston Robot Remix"},{"eventKey":"2014txrr","name":null},{"eventKey":"2014txsa","name":"Alamo"},{"eventKey":"2014utwv","name":"Utah"},{"eventKey":"2014vari","name":"Virginia"},{"eventKey":"2014varr","name":null},{"eventKey":"2014waahs","name":"Auburn"},{"eventKey":"2014waamv","name":"Auburn Mountainview"},{"eventKey":"2014wache","name":"Eastern Washington University"},{"eventKey":"2014waell","name":"Central Washington University"},{"eventKey":"2014wagg","name":"WA Girls' Generation"},{"eventKey":"2014wamou","name":"Mt. Vernon"},{"eventKey":"2014washo","name":"Shorewood"},{"eventKey":"2014wasno","name":"Glacier Peak"},{"eventKey":"2014wimi","name":"Wisconsin"},{"eventKey":"2014wirf","name":null},{"eventKey":"2014wiwi","name":null},{"eventKey":"2014wmri","name":"West Michigan Robotics Invitational"},{"eventKey":"2014wvro","name":"WVROX"}]